mumuipc.py
mumuipc_py-0.0.2.dist-info/licenses/LICENSE
mumuipc_py-0.0.2.dist-info/METADATA
mumuipc_py-0.0.2.dist-info/WHEEL
mumuipc_py-0.0.2.dist-info/top_level.txt
mumuipc_py-0.0.2.dist-info/RECORD
